tjfu/__init__.py
tjfu/route.py
tjfu/tj_socket.py
tjfu/tj_utils.py
tjfu/tjfu.py
tjfu-3.3.0.dist-info/METADATA
tjfu-3.3.0.dist-info/WHEEL
tjfu-3.3.0.dist-info/top_level.txt
tjfu-3.3.0.dist-info/RECORD
