Metadata-Version: 2.1
Name: tjfu
Version: 3.3.0
Summary: Python library helps optimize Flask development to be flexible and object-oriented.
Home-page: https://github.com/duynguyen02/tjfu
Author: Duy Nguyen
License: UNKNOWN
Keywords: Python,Flask
Platform: UNKNOWN
Classifier: Intended Audience :: Developers
Classifier: License :: OSI Approved :: MIT License
Classifier: Programming Language :: Python
Classifier: Programming Language :: Python :: 3.9
Classifier: Operating System :: OS Independent
Requires-Python: >=3.9
Requires-Dist: flask
Requires-Dist: flask-cors
Requires-Dist: flask-jwt-extended
Requires-Dist: flask-limiter
Requires-Dist: flask-socketio
